meta_truemoney_api/__init__.py
meta_truemoney_api/client.py
meta_truemoney_api-1.0.3.dist-info/LICENSE
meta_truemoney_api-1.0.3.dist-info/METADATA
meta_truemoney_api-1.0.3.dist-info/WHEEL
meta_truemoney_api-1.0.3.dist-info/top_level.txt
meta_truemoney_api-1.0.3.dist-info/RECORD
