Metadata-Version: 2.1
Name: meta-truemoney-api
Version: 1.0.3
Summary: API สำหรับเชื่อมต่อระบบซองอั่งเปา TrueMoney
Home-page: https://github.com/yourname/meta-truemoney-api
Author: DEVPARK
Author-email: DevPark <0924011344aa@gmail.com>
License: MIT
Project-URL: Homepage, https://github.com/Park000007/meta-truemoney-api
Project-URL: Bug Tracker, https://github.com/Park000007/meta-truemoney-api/issues
Requires-Python: >=3.8
License-File: LICENSE
Requires-Dist: requests
